standing/__init__.py
standing/core.py
standing/plot.py
standing-0.1.0.dist-info/AUTHORS.rst
standing-0.1.0.dist-info/LICENSE
standing-0.1.0.dist-info/METADATA
standing-0.1.0.dist-info/WHEEL
standing-0.1.0.dist-info/top_level.txt
standing-0.1.0.dist-info/RECORD
