Metadata-Version: 2.1
Name: standing
Version: 0.1.0
Summary: Compute wavenumber-frequency spectra and decomposition into standing and travelling components
Home-page: https://github.com/oliverwm1/standing
Author: Oliver Watt-Meyer
Author-email: oliverwatt@gmail.com
License: MIT license
Keywords: standing
Platform: UNKNOWN
Classifier: Development Status :: 2 - Pre-Alpha
Classifier: Intended Audience :: Developers
Classifier: License :: OSI Approved :: MIT License
Classifier: Natural Language :: English
Classifier: Programming Language :: Python :: 3
Classifier: Programming Language :: Python :: 3.5
Classifier: Programming Language :: Python :: 3.6
Classifier: Programming Language :: Python :: 3.7
Classifier: Programming Language :: Python :: 3.8
Requires-Python: >=3.5
